sdf_py/__init__.py
sdf_py/cli.py
sdf_py/exceptions.py
sdf_py/reader.py
sdf_py/writer.py
synaptic_format-1.0.0.dist-info/METADATA
synaptic_format-1.0.0.dist-info/WHEEL
synaptic_format-1.0.0.dist-info/entry_points.txt
synaptic_format-1.0.0.dist-info/top_level.txt
synaptic_format-1.0.0.dist-info/RECORD
