Metadata-Version: 2.4
Name: synaptic-format
Version: 1.0.0
Summary: The official Python implementation for the Synaptic Data Format (SDF), a modern, tensor-native format for AI.
Author-email: Louati Mahdi <louatimahdi390@gmail.com>
Project-URL: Homepage, https://github.com/mahdi123-tech
Project-URL: Bug Tracker, https://github.com/mahdi123-tech
Classifier: Programming Language :: Python :: 3
Classifier: License :: OSI Approved :: MIT License
Classifier: Operating System :: OS Independent
Classifier: Topic :: Scientific/Engineering :: Artificial Intelligence
Classifier: Topic :: Software Development :: Libraries :: Python Modules
Requires-Python: >=3.7
Requires-Dist: numpy
Requires-Dist: protobuf
Requires-Dist: pyyaml
Requires-Dist: click
